sag_py_auth_brand/__init__.py
sag_py_auth_brand/brand_jwt_auth.py
sag_py_auth_brand/models.py
sag_py_auth_brand/py.typed
sag_py_auth_brand/request_brand_context.py
sag_py_auth_brand/request_brand_logging_filter.py
sag_py_auth_brand-1.2.3.dist-info/licenses/LICENSE.txt
sag_py_auth_brand-1.2.3.dist-info/METADATA
sag_py_auth_brand-1.2.3.dist-info/WHEEL
sag_py_auth_brand-1.2.3.dist-info/top_level.txt
sag_py_auth_brand-1.2.3.dist-info/RECORD
