Metadata-Version: 2.4
Name: sag-py-auth-brand
Version: 1.2.3
Summary: Keycloak brand/instance authentication for python projects
Home-page: https://github.com/SamhammerAG/sag_py_auth_brand
Author: Samhammer AG
Author-email: support@samhammer.de
License: MIT
Project-URL: Documentation, https://github.com/SamhammerAG/sag_py_auth_brand
Project-URL: Bug Reports, https://github.com/SamhammerAG/sag_py_auth_brand/issues
Project-URL: Source, https://github.com/SamhammerAG/sag_py_auth_brand
Keywords: auth,fastapi,keycloak
Classifier: Programming Language :: Python :: 3
Classifier: License :: OSI Approved :: MIT License
Classifier: Operating System :: OS Independent
Classifier: Topic :: Software Development :: Libraries :: Python Modules
Classifier: Topic :: Software Development :: Libraries
Classifier: Topic :: Software Development
Requires-Python: >=3.12
License-File: LICENSE.txt
Requires-Dist: contextvars>=2.4
Requires-Dist: fastapi[standard]>=0.115.12
Requires-Dist: sag-py-auth>=1.2.2
Provides-Extra: dev
Requires-Dist: pytest; extra == "dev"
Dynamic: author
Dynamic: author-email
Dynamic: classifier
Dynamic: description
Dynamic: description-content-type
Dynamic: home-page
Dynamic: keywords
Dynamic: license
Dynamic: license-file
Dynamic: project-url
Dynamic: provides-extra
Dynamic: requires-dist
Dynamic: requires-python
Dynamic: summary
